Workbook

Sheet Raw_Sales_Data
A1: Transaction_ID | B1: Transaction_Date | C1: Customer_Info | D1: Customer_Id | E1: Customer_Name | F1: Customer_City | G1: Product_Info | H1: Product_ID | I1: Product_Name | J1: Location | K1: Quantity | L1: Unit_Price | M1: Payment_Mode | N1: Salesperson | O1: Category | P1: Brand | Q1: Gst_Rate | R1: Sales_Value | S1: GST_Amount | T1: Total_Value
A2: TXN001 | B2: 46212 | C2: C001-Nandana-Trivandrum | D2: {=_xlfn.TEXTSPLIT(TRIM(C2),"-")} -> C001 | E2: Nandana | F2: Trivandrum | G2: P101-Laptop | H2: {=_xlfn.TEXTSPLIT(TRIM(G2),"-")} -> P101 | I2: Laptop | J2: Trivandrum | K2: 12 | L2: 55000 | M2: Credit Card | N2: Ravi | O2: =VLOOKUP(H2,Product_Master!$A:$E,3,FALSE) -> Electronics | P2: =VLOOKUP(H2,Product_Master!$A:$E,4,FALSE) -> Dell | Q2: =VLOOKUP(H2,Product_Master!$A:$E,5,FALSE) -> 0.18 | R2: =K2*L2 -> 660000 | S2: =R2*Q2 -> 118800 | T2: =R2+S2 -> 778800
A3: TXN002 | B3: 46217 | C3: C002-Joel-Trivandrum | D3: {=_xlfn.TEXTSPLIT(TRIM(C3),"-")} -> C002 | E3: Joel | F3: Trivandrum | G3: P102-Monitor | H3: {=_xlfn.TEXTSPLIT(TRIM(G3),"-")} -> P102 | I3: Monitor | J3: Trivandrum | K3: 10 | L3: 15000 | M3: UPI | N3: Anu | O3: =VLOOKUP(H3,Product_Master!$A:$E,3,FALSE) -> Electronics | P3: =VLOOKUP(H3,Product_Master!$A:$E,4,FALSE) -> LG | Q3: =VLOOKUP(H3,Product_Master!$A:$E,5,FALSE) -> 0.18 | R3: =K3*L3 -> 150000 | S3: =R3*Q3 -> 27000 | T3: =R3+S3 -> 177000 | AA3: QUESTIONS | AB3: ANSWERS
A4: TXN003 | B4: 46210 | C4: C003-Arjun-Kannur | D4: {=_xlfn.TEXTSPLIT(TRIM(C4),"-")} -> C003 | E4: Arjun | F4: Kannur | G4: P101-Laptop | H4: {=_xlfn.TEXTSPLIT(TRIM(G4),"-")} -> P101 | I4: Laptop | J4: Kannur | K4: 9 | L4: 55000 | M4: Debit Card | N4: Ravi | O4: =VLOOKUP(H4,Product_Master!$A:$E,3,FALSE) -> Electronics | P4: =VLOOKUP(H4,Product_Master!$A:$E,4,FALSE) -> Dell | Q4: =VLOOKUP(H4,Product_Master!$A:$E,5,FALSE) -> 0.18 | R4: =K4*L4 -> 495000 | S4: =R4*Q4 -> 89100 | T4: =R4+S4 -> 584100 | V4: TOTAL TRANSACTIONS= | W4: =COUNTA(A2:A251) -> 250
A5: TXN004 | B5: 46226 | C5: C004-Lakshmi-Kollam | D5: {=_xlfn.TEXTSPLIT(TRIM(C5),"-")} -> C004 | E5: Lakshmi | F5: Kollam | G5: P101-Laptop | H5: {=_xlfn.TEXTSPLIT(TRIM(G5),"-")} -> P101 | I5: Laptop | J5: Kollam | K5: 3 | L5: 55000 | M5: Cash | N5: Meera | O5: =VLOOKUP(H5,Product_Master!$A:$E,3,FALSE) -> Electronics | P5: =VLOOKUP(H5,Product_Master!$A:$E,4,FALSE) -> Dell | Q5: =VLOOKUP(H5,Product_Master!$A:$E,5,FALSE) -> 0.18 | R5: =K5*L5 -> 165000 | S5: =R5*Q5 -> 29700 | T5: =R5+S5 -> 194700 | AA5: Which product generated the highest sales value? | AB5: LAPTOP
A6: TXN005 | B6: 46206 | C6: C005-Akhil-Kannur | D6: {=_xlfn.TEXTSPLIT(TRIM(C6),"-")} -> C005 | E6: Akhil | F6: Kannur | G6: P106-Printer | H6: {=_xlfn.TEXTSPLIT(TRIM(G6),"-")} -> P106 | I6: Printer | J6: Kannur | K6: 2 | L6: 12500 | M6: UPI | N6: Meera | O6: =VLOOKUP(H6,Product_Master!$A:$E,3,FALSE) -> Electronics | P6: =VLOOKUP(H6,Product_Master!$A:$E,4,FALSE) -> Canon | Q6: =VLOOKUP(H6,Product_Master!$A:$E,5,FALSE) -> 0.18 | R6: =K6*L6 -> 25000 | S6: =R6*Q6 -> 4500 | T6: =R6+S6 -> 29500 | V6: TOTAL QUANTITY SOLD= | W6: =SUM(K2:K251) -> 1632
A7: TXN006 | B7: 46218 | C7: C006-Sneha-Kollam | D7: {=_xlfn.TEXTSPLIT(TRIM(C7),"-")} -> C006 | E7: Sneha | F7: Kollam | G7: P101-Laptop | H7: {=_xlfn.TEXTSPLIT(TRIM(G7),"-")} -> P101 | I7: Laptop | J7: Kollam | K7: 12 | L7: 55000 | M7: UPI | N7: Suresh | O7: =VLOOKUP(H7,Product_Master!$A:$E,3,FALSE) -> Electronics | P7: =VLOOKUP(H7,Product_Master!$A:$E,4,FALSE) -> Dell | Q7: =VLOOKUP(H7,Product_Master!$A:$E,5,FALSE) -> 0.18 | R7: =K7*L7 -> 660000 | S7: =R7*Q7 -> 118800 | T7: =R7+S7 -> 778800 | AA7: Which salesperson generated the highest sales? | AB7: SURESH
A8: TXN007 | B8: 46210 | C8: C007-Mohammed-Kollam | D8: {=_xlfn.TEXTSPLIT(TRIM(C8),"-")} -> C007 | E8: Mohammed | F8: Kollam | G8: P106-Printer | H8: {=_xlfn.TEXTSPLIT(TRIM(G8),"-")} -> P106 | I8: Printer | J8: Kollam | K8: 10 | L8: 12500 | M8: UPI | N8: Anu | O8: =VLOOKUP(H8,Product_Master!$A:$E,3,FALSE) -> Electronics | P8: =VLOOKUP(H8,Product_Master!$A:$E,4,FALSE) -> Canon | Q8: =VLOOKUP(H8,Product_Master!$A:$E,5,FALSE) -> 0.18 | R8: =K8*L8 -> 125000 | S8: =R8*Q8 -> 22500 | T8: =R8+S8 -> 147500 | V8: TOTAL SALES VALUE= | W8: =SUM(R2:R251) -> 20100550
A9: TXN008 | B9: 46231 | C9: C008-Farhan-Kannur | D9: {=_xlfn.TEXTSPLIT(TRIM(C9),"-")} -> C008 | E9: Farhan | F9: Kannur | G9: P105-Headphones | H9: {=_xlfn.TEXTSPLIT(TRIM(G9),"-")} -> P105 | I9: Headphones | J9: Kannur | K9: 2 | L9: 2500 | M9: UPI | N9: Suresh | O9: =VLOOKUP(H9,Product_Master!$A:$E,3,FALSE) -> Accessories | P9: =VLOOKUP(H9,Product_Master!$A:$E,4,FALSE) -> Sony | Q9: =VLOOKUP(H9,Product_Master!$A:$E,5,FALSE) -> 0.18 | R9: =K9*L9 -> 5000 | S9: =R9*Q9 -> 900 | T9: =R9+S9 -> 5900 | AA9: Which location generated the highest sales? | AB9: THRISSUR
A10: TXN009 | B10: 46215 | C10: C009-Sanjay-Alappuzha | D10: {=_xlfn.TEXTSPLIT(TRIM(C10),"-")} -> C009 | E10: Sanjay | F10: Alappuzha | G10: P106-Printer | H10: {=_xlfn.TEXTSPLIT(TRIM(G10),"-")} -> P106 | I10: Printer | J10: Alappuzha | K10: 3 | L10: 12500 | M10: Credit Card | N10: Meera | O10: =VLOOKUP(H10,Product_Master!$A:$E,3,FALSE) -> Electronics | P10: =VLOOKUP(H10,Product_Master!$A:$E,4,FALSE) -> Canon | Q10: =VLOOKUP(H10,Product_Master!$A:$E,5,FALSE) -> 0.18 | R10: =K10*L10 -> 37500 | S10: =R10*Q10 -> 6750 | T10: =R10+S10 -> 44250 | V10: AVERAGE TRANSATION VALUE= | W10: =AVERAGE(T2:T251) -> 94874.596
A11: TXN010 | B11: 46227 | C11: C010-Swathi-Trivandrum | D11: {=_xlfn.TEXTSPLIT(TRIM(C11),"-")} -> C010 | E11: Swathi | F11: Trivandrum | G11: P103-Keyboard | H11: {=_xlfn.TEXTSPLIT(TRIM(G11),"-")} -> P103 | I11: Keyboard | J11: Trivandrum | K11: 9 | L11: 1200 | M11: Credit Card | N11: Suresh | O11: =VLOOKUP(H11,Product_Master!$A:$E,3,FALSE) -> Accessories | P11: =VLOOKUP(H11,Product_Master!$A:$E,4,FALSE) -> Logitech | Q11: =VLOOKUP(H11,Product_Master!$A:$E,5,FALSE) -> 0.18 | R11: =K11*L11 -> 10800 | S11: =R11*Q11 -> 1944 | T11: =R11+S11 -> 12744 | AA11: Which product category contributed the most sales? | AB11: ELECTRONICS
A12: TXN011 | B12: 46214 | C12: C011-Vishnu-Kollam | D12: {=_xlfn.TEXTSPLIT(TRIM(C12),"-")} -> C011 | E12: Vishnu | F12: Kollam | G12: P104-Mouse | H12: {=_xlfn.TEXTSPLIT(TRIM(G12),"-")} -> P104 | I12: Mouse | J12: Kollam | K12: 11 | L12: 750 | M12: Credit Card | N12: Anu | O12: =VLOOKUP(H12,Product_Master!$A:$E,3,FALSE) -> Accessories | P12: =VLOOKUP(H12,Product_Master!$A:$E,4,FALSE) -> HP | Q12: =VLOOKUP(H12,Product_Master!$A:$E,5,FALSE) -> 0.18 | R12: =K12*L12 -> 8250 | S12: =R12*Q12 -> 1485 | T12: =R12+S12 -> 9735 | V12: MININUM TRANSATION VALUE= | W12: =MIN(T2:T251) -> 885
A13: TXN012 | B13: 46210 | C13: C012-Nikhil-Thrissur | D13: {=_xlfn.TEXTSPLIT(TRIM(C13),"-")} -> C012 | E13: Nikhil | F13: Thrissur | G13: P105-Headphones | H13: {=_xlfn.TEXTSPLIT(TRIM(G13),"-")} -> P105 | I13: Headphones | J13: Thrissur | K13: 2 | L13: 2500 | M13: Cash | N13: Ravi | O13: =VLOOKUP(H13,Product_Master!$A:$E,3,FALSE) -> Accessories | P13: =VLOOKUP(H13,Product_Master!$A:$E,4,FALSE) -> Sony | Q13: =VLOOKUP(H13,Product_Master!$A:$E,5,FALSE) -> 0.18 | R13: =K13*L13 -> 5000 | S13: =R13*Q13 -> 900 | T13: =R13+S13 -> 5900 | AA13: Which payment method was used most frequently? | AB13: CASH
A14: TXN013 | B14: 46218 | C14: C013-Nandana-Alappuzha | D14: {=_xlfn.TEXTSPLIT(TRIM(C14),"-")} -> C013 | E14: Nandana | F14: Alappuzha | G14: P107-Webcam | H14: {=_xlfn.TEXTSPLIT(TRIM(G14),"-")} -> P107 | I14: Webcam | J14: Alappuzha | K14: 11 | L14: 3500 | M14: Cash | N14: Ravi | O14: =VLOOKUP(H14,Product_Master!$A:$E,3,FALSE) -> Electronics | P14: =VLOOKUP(H14,Product_Master!$A:$E,4,FALSE) -> Logitech | Q14: =VLOOKUP(H14,Product_Master!$A:$E,5,FALSE) -> 0.18 | R14: =K14*L14 -> 38500 | S14: =R14*Q14 -> 6930 | T14: =R14+S14 -> 45430 | V14: MAXIMUM TRANSATION VALUE= | W14: =MAX(T2:T251) -> 778800
A15: TXN014 | B15: 46216 | C15: C014-Divya-Kollam | D15: {=_xlfn.TEXTSPLIT(TRIM(C15),"-")} -> C014 | E15: Divya | F15: Kollam | G15: P107-Webcam | H15: {=_xlfn.TEXTSPLIT(TRIM(G15),"-")} -> P107 | I15: Webcam | J15: Kollam | K15: 10 | L15: 3500 | M15: Credit Card | N15: Ravi | O15: =VLOOKUP(H15,Product_Master!$A:$E,3,FALSE) -> Electronics | P15: =VLOOKUP(H15,Product_Master!$A:$E,4,FALSE) -> Logitech | Q15: =VLOOKUP(H15,Product_Master!$A:$E,5,FALSE) -> 0.18 | R15: =K15*L15 -> 35000 | S15: =R15*Q15 -> 6300 | T15: =R15+S15 -> 41300 | AA15: What is the average value of a transaction? | AB15: =AVERAGE(T2:T251) -> 94874.596
A16: TXN015 | B16: 46231 | C16: C015-Meera-Alappuzha | D16: {=_xlfn.TEXTSPLIT(TRIM(C16),"-")} -> C015 | E16: Meera | F16: Alappuzha | G16: P102-Monitor | H16: {=_xlfn.TEXTSPLIT(TRIM(G16),"-")} -> P102 | I16: Monitor | J16: Alappuzha | K16: 1 | L16: 15000 | M16: Credit Card | N16: Ravi | O16: =VLOOKUP(H16,Product_Master!$A:$E,3,FALSE) -> Electronics | P16: =VLOOKUP(H16,Product_Master!$A:$E,4,FALSE) -> LG | Q16: =VLOOKUP(H16,Product_Master!$A:$E,5,FALSE) -> 0.18 | R16: =K16*L16 -> 15000 | S16: =R16*Q16 -> 2700 | T16: =R16+S16 -> 17700
A17: TXN016 | B17: 46216 | C17: C016-Farhan-Thrissur | D17: {=_xlfn.TEXTSPLIT(TRIM(C17),"-")} -> C016 | E17: Farhan | F17: Thrissur | G17: P102-Monitor | H17: {=_xlfn.TEXTSPLIT(TRIM(G17),"-")} -> P102 | I17: Monitor | J17: Thrissur | K17: 7 | L17: 15000 | M17: Debit Card | N17: Asha | O17: =VLOOKUP(H17,Product_Master!$A:$E,3,FALSE) -> Electronics | P17: =VLOOKUP(H17,Product_Master!$A:$E,4,FALSE) -> LG | Q17: =VLOOKUP(H17,Product_Master!$A:$E,5,FALSE) -> 0.18 | R17: =K17*L17 -> 105000 | S17: =R17*Q17 -> 18900 | T17: =R17+S17 -> 123900 | V17: LOCATION | W17: TRANSACTION | X17: TOTAL SALES | AA17: What observations can you make about the sales data? | AB17: Thrissur generating the highest sales despite Kollam recording the highest number of transactions.
A18: TXN017 | B18: 46232 | C18: C017-Sanjay-Kochi | D18: {=_xlfn.TEXTSPLIT(TRIM(C18),"-")} -> C017 | E18: Sanjay | F18: Kochi | G18: P102-Monitor | H18: {=_xlfn.TEXTSPLIT(TRIM(G18),"-")} -> P102 | I18: Monitor | J18: Kochi | K18: 11 | L18: 15000 | M18: Cash | N18: Meera | O18: =VLOOKUP(H18,Product_Master!$A:$E,3,FALSE) -> Electronics | P18: =VLOOKUP(H18,Product_Master!$A:$E,4,FALSE) -> LG | Q18: =VLOOKUP(H18,Product_Master!$A:$E,5,FALSE) -> 0.18 | R18: =K18*L18 -> 165000 | S18: =R18*Q18 -> 29700 | T18: =R18+S18 -> 194700 | V18: THRISSUR | W18: =COUNTIF($J$1:$J$251,V18) -> 31 | X18: =SUMIF($J$2:$J$251,V18,$R$2:$R$251) -> 3974450 | AB18: Malappuram had the lowest number of transactions and Alappuzha has the lowest sales values.
A19: TXN018 | B19: 46218 | C19: C018-Priya-Kollam | D19: {=_xlfn.TEXTSPLIT(TRIM(C19),"-")} -> C018 | E19: Priya | F19: Kollam | G19: P107-Webcam | H19: {=_xlfn.TEXTSPLIT(TRIM(G19),"-")} -> P107 | I19: Webcam | J19: Kollam | K19: 3 | L19: 3500 | M19: Cash | N19: Asha | O19: =VLOOKUP(H19,Product_Master!$A:$E,3,FALSE) -> Electronics | P19: =VLOOKUP(H19,Product_Master!$A:$E,4,FALSE) -> Logitech | Q19: =VLOOKUP(H19,Product_Master!$A:$E,5,FALSE) -> 0.18 | R19: =K19*L19 -> 10500 | S19: =R19*Q19 -> 1890 | T19: =R19+S19 -> 12390 | V19: KOLLAM | W19: =COUNTIF($J$1:$J$251,V19) -> 43 | X19: =SUMIF($J$2:$J$251,V19,$R$2:$R$251) -> 3080650
A20: TXN019 | B20: 46220 | C20: C019-Neha-Trivandrum | D20: {=_xlfn.TEXTSPLIT(TRIM(C20),"-")} -> C019 | E20: Neha | F20: Trivandrum | G20: P105-Headphones | H20: {=_xlfn.TEXTSPLIT(TRIM(G20),"-")} -> P105 | I20: Headphones | J20: Trivandrum | K20: 11 | L20: 2500 | M20: Credit Card | N20: Ravi | O20: =VLOOKUP(H20,Product_Master!$A:$E,3,FALSE) -> Accessories | P20: =VLOOKUP(H20,Product_Master!$A:$E,4,FALSE) -> Sony | Q20: =VLOOKUP(H20,Product_Master!$A:$E,5,FALSE) -> 0.18 | R20: =K20*L20 -> 27500 | S20: =R20*Q20 -> 4950 | T20: =R20+S20 -> 32450 | V20: TRIVANDRUM | W20: =COUNTIF($J$1:$J$251,V20) -> 34 | X20: =SUMIF($J$2:$J$251,V20,$R$2:$R$251) -> 2843750
A21: TXN020 | B21: 46214 | C21: C020-Sneha-Kozhikode | D21: {=_xlfn.TEXTSPLIT(TRIM(C21),"-")} -> C020 | E21: Sneha | F21: Kozhikode | G21: P101-Laptop | H21: {=_xlfn.TEXTSPLIT(TRIM(G21),"-")} -> P101 | I21: Laptop | J21: Kozhikode | K21: 10 | L21: 55000 | M21: UPI | N21: Anu | O21: =VLOOKUP(H21,Product_Master!$A:$E,3,FALSE) -> Electronics | P21: =VLOOKUP(H21,Product_Master!$A:$E,4,FALSE) -> Dell | Q21: =VLOOKUP(H21,Product_Master!$A:$E,5,FALSE) -> 0.18 | R21: =K21*L21 -> 550000 | S21: =R21*Q21 -> 99000 | T21: =R21+S21 -> 649000 | V21: KANNUR | W21: =COUNTIF($J$1:$J$251,V21) -> 36 | X21: =SUMIF($J$2:$J$251,V21,$R$2:$R$251) -> 2697900
A22: TXN021 | B22: 46211 | C22: C021-Sneha-Kollam | D22: {=_xlfn.TEXTSPLIT(TRIM(C22),"-")} -> C021 | E22: Sneha | F22: Kollam | G22: P104-Mouse | H22: {=_xlfn.TEXTSPLIT(TRIM(G22),"-")} -> P104 | I22: Mouse | J22: Kollam | K22: 1 | L22: 750 | M22: UPI | N22: Anu | O22: =VLOOKUP(H22,Product_Master!$A:$E,3,FALSE) -> Accessories | P22: =VLOOKUP(H22,Product_Master!$A:$E,4,FALSE) -> HP | Q22: =VLOOKUP(H22,Product_Master!$A:$E,5,FALSE) -> 0.18 | R22: =K22*L22 -> 750 | S22: =R22*Q22 -> 135 | T22: =R22+S22 -> 885 | V22: KOZHIKODE | W22: =COUNTIF($J$1:$J$251,V22) -> 25 | X22: =SUMIF($J$2:$J$251,V22,$R$2:$R$251) -> 2433900
A23: TXN022 | B23: 46228 | C23: C022-Joel-Alappuzha | D23: {=_xlfn.TEXTSPLIT(TRIM(C23),"-")} -> C022 | E23: Joel | F23: Alappuzha | G23: P102-Monitor | H23: {=_xlfn.TEXTSPLIT(TRIM(G23),"-")} -> P102 | I23: Monitor | J23: Alappuzha | K23: 9 | L23: 15000 | M23: Credit Card | N23: Suresh | O23: =VLOOKUP(H23,Product_Master!$A:$E,3,FALSE) -> Electronics | P23: =VLOOKUP(H23,Product_Master!$A:$E,4,FALSE) -> LG | Q23: =VLOOKUP(H23,Product_Master!$A:$E,5,FALSE) -> 0.18 | R23: =K23*L23 -> 135000 | S23: =R23*Q23 -> 24300 | T23: =R23+S23 -> 159300 | V23: KOCHI | W23: =COUNTIF($J$1:$J$251,V23) -> 29 | X23: =SUMIF($J$2:$J$251,V23,$R$2:$R$251) -> 2040300
A24: TXN023 | B24: 46231 | C24: C023-Ravi-Kozhikode | D24: {=_xlfn.TEXTSPLIT(TRIM(C24),"-")} -> C023 | E24: Ravi | F24: Kozhikode | G24: P105-Headphones | H24: {=_xlfn.TEXTSPLIT(TRIM(G24),"-")} -> P105 | I24: Headphones | J24: Kozhikode | K24: 9 | L24: 2500 | M24: Debit Card | N24: Ravi | O24: =VLOOKUP(H24,Product_Master!$A:$E,3,FALSE) -> Accessories | P24: =VLOOKUP(H24,Product_Master!$A:$E,4,FALSE) -> Sony | Q24: =VLOOKUP(H24,Product_Master!$A:$E,5,FALSE) -> 0.18 | R24: =K24*L24 -> 22500 | S24: =R24*Q24 -> 4050 | T24: =R24+S24 -> 26550 | V24: MALAPPURAM | W24: =COUNTIF($J$1:$J$251,V24) -> 22 | X24: =SUMIF($J$2:$J$251,V24,$R$2:$R$251) -> 1604200
A25: TXN024 | B25: 46225 | C25: C024-Ravi-Kannur | D25: {=_xlfn.TEXTSPLIT(TRIM(C25),"-")} -> C024 | E25: Ravi | F25: Kannur | G25: P105-Headphones | H25: {=_xlfn.TEXTSPLIT(TRIM(G25),"-")} -> P105 | I25: Headphones | J25: Kannur | K25: 7 | L25: 2500 | M25: Cash | N25: Suresh | O25: =VLOOKUP(H25,Product_Master!$A:$E,3,FALSE) -> Accessories | P25: =VLOOKUP(H25,Product_Master!$A:$E,4,FALSE) -> Sony | Q25: =VLOOKUP(H25,Product_Master!$A:$E,5,FALSE) -> 0.18 | R25: =K25*L25 -> 17500 | S25: =R25*Q25 -> 3150 | T25: =R25+S25 -> 20650 | V25: ALAPPUZHA | W25: =COUNTIF($J$1:$J$251,V25) -> 30 | X25: =SUMIF($J$2:$J$251,V25,$R$2:$R$251) -> 1425400
A26: TXN025 | B26: 46211 | C26: C025-Meera-Alappuzha | D26: {=_xlfn.TEXTSPLIT(TRIM(C26),"-")} -> C025 | E26: Meera | F26: Alappuzha | G26: P102-Monitor | H26: {=_xlfn.TEXTSPLIT(TRIM(G26),"-")} -> P102 | I26: Monitor | J26: Alappuzha | K26: 4 | L26: 15000 | M26: Cash | N26: Anu | O26: =VLOOKUP(H26,Product_Master!$A:$E,3,FALSE) -> Electronics | P26: =VLOOKUP(H26,Product_Master!$A:$E,4,FALSE) -> LG | Q26: =VLOOKUP(H26,Product_Master!$A:$E,5,FALSE) -> 0.18 | R26: =K26*L26 -> 60000 | S26: =R26*Q26 -> 10800 | T26: =R26+S26 -> 70800
A27: TXN026 | B27: 46206 | C27: C026-Asha-Kannur | D27: {=_xlfn.TEXTSPLIT(TRIM(C27),"-")} -> C026 | E27: Asha | F27: Kannur | G27: P104-Mouse | H27: {=_xlfn.TEXTSPLIT(TRIM(G27),"-")} -> P104 | I27: Mouse | J27: Kannur | K27: 1 | L27: 750 | M27: UPI | N27: Ravi | O27: =VLOOKUP(H27,Product_Master!$A:$E,3,FALSE) -> Accessories | P27: =VLOOKUP(H27,Product_Master!$A:$E,4,FALSE) -> HP | Q27: =VLOOKUP(H27,Product_Master!$A:$E,5,FALSE) -> 0.18 | R27: =K27*L27 -> 750 | S27: =R27*Q27 -> 135 | T27: =R27+S27 -> 885
A28: TXN027 | B28: 46220 | C28: C027-Mohammed-Kochi | D28: {=_xlfn.TEXTSPLIT(TRIM(C28),"-")} -> C027 | E28: Mohammed | F28: Kochi | G28: P106-Printer | H28: {=_xlfn.TEXTSPLIT(TRIM(G28),"-")} -> P106 | I28: Printer | J28: Kochi | K28: 2 | L28: 12500 | M28: Cash | N28: Suresh | O28: =VLOOKUP(H28,Product_Master!$A:$E,3,FALSE) -> Electronics | P28: =VLOOKUP(H28,Product_Master!$A:$E,4,FALSE) -> Canon | Q28: =VLOOKUP(H28,Product_Master!$A:$E,5,FALSE) -> 0.18 | R28: =K28*L28 -> 25000 | S28: =R28*Q28 -> 4500 | T28: =R28+S28 -> 29500 | V28: HIGHEST SELLING LOCATION= | W28: THRISSUR
A29: TXN028 | B29: 46229 | C29: C028-Arjun-Kozhikode | D29: {=_xlfn.TEXTSPLIT(TRIM(C29),"-")} -> C028 | E29: Arjun | F29: Kozhikode | G29: P108-SSD | H29: {=_xlfn.TEXTSPLIT(TRIM(G29),"-")} -> P108 | I29: SSD | J29: Kozhikode | K29: 4 | L29: 6500 | M29: Debit Card | N29: Ravi | O29: =VLOOKUP(H29,Product_Master!$A:$E,3,FALSE) -> Storage | P29: =VLOOKUP(H29,Product_Master!$A:$E,4,FALSE) -> Samsung | Q29: =VLOOKUP(H29,Product_Master!$A:$E,5,FALSE) -> 0.18 | R29: =K29*L29 -> 26000 | S29: =R29*Q29 -> 4680 | T29: =R29+S29 -> 30680
A30: TXN029 | B30: 46217 | C30: C029-Priya-Trivandrum | D30: {=_xlfn.TEXTSPLIT(TRIM(C30),"-")} -> C029 | E30: Priya | F30: Trivandrum | G30: P107-Webcam | H30: {=_xlfn.TEXTSPLIT(TRIM(G30),"-")} -> P107 | I30: Webcam | J30: Trivandrum | K30: 6 | L30: 3500 | M30: Debit Card | N30: Anu | O30: =VLOOKUP(H30,Product_Master!$A:$E,3,FALSE) -> Electronics | P30: =VLOOKUP(H30,Product_Master!$A:$E,4,FALSE) -> Logitech | Q30: =VLOOKUP(H30,Product_Master!$A:$E,5,FALSE) -> 0.18 | R30: =K30*L30 -> 21000 | S30: =R30*Q30 -> 3780 | T30: =R30+S30 -> 24780
A31: TXN030 | B31: 46227 | C31: C030-Farhan-Trivandrum | D31: {=_xlfn.TEXTSPLIT(TRIM(C31),"-")} -> C030 | E31: Farhan | F31: Trivandrum | G31: P101-Laptop | H31: {=_xlfn.TEXTSPLIT(TRIM(G31),"-")} -> P101 | I31: Laptop | J31: Trivandrum | K31: 7 | L31: 55000 | M31: UPI | N31: Ravi | O31: =VLOOKUP(H31,Product_Master!$A:$E,3,FALSE) -> Electronics | P31: =VLOOKUP(H31,Product_Master!$A:$E,4,FALSE) -> Dell | Q31: =VLOOKUP(H31,Product_Master!$A:$E,5,FALSE) -> 0.18 | R31: =K31*L31 -> 385000 | S31: =R31*Q31 -> 69300 | T31: =R31+S31 -> 454300 | V31: PAYMENT METHORDS | W31: TRANSACTION
A32: TXN031 | B32: 46217 | C32: C031-Arjun-Kannur | D32: {=_xlfn.TEXTSPLIT(TRIM(C32),"-")} -> C031 | E32: Arjun | F32: Kannur | G32: P108-SSD | H32: {=_xlfn.TEXTSPLIT(TRIM(G32),"-")} -> P108 | I32: SSD | J32: Kannur | K32: 3 | L32: 6500 | M32: Cash | N32: Suresh | O32: =VLOOKUP(H32,Product_Master!$A:$E,3,FALSE) -> Storage | P32: =VLOOKUP(H32,Product_Master!$A:$E,4,FALSE) -> Samsung | Q32: =VLOOKUP(H32,Product_Master!$A:$E,5,FALSE) -> 0.18 | R32: =K32*L32 -> 19500 | S32: =R32*Q32 -> 3510 | T32: =R32+S32 -> 23010 | V32: CASH | W32: =COUNTIF($M$2:$M$251,V32) -> 67
A33: TXN032 | B33: 46207 | C33: C032-Divya-Trivandrum | D33: {=_xlfn.TEXTSPLIT(TRIM(C33),"-")} -> C032 | E33: Divya | F33: Trivandrum | G33: P108-SSD | H33: {=_xlfn.TEXTSPLIT(TRIM(G33),"-")} -> P108 | I33: SSD | J33: Trivandrum | K33: 9 | L33: 6500 | M33: UPI | N33: Anu | O33: =VLOOKUP(H33,Product_Master!$A:$E,3,FALSE) -> Storage | P33: =VLOOKUP(H33,Product_Master!$A:$E,4,FALSE) -> Samsung | Q33: =VLOOKUP(H33,Product_Master!$A:$E,5,FALSE) -> 0.18 | R33: =K33*L33 -> 58500 | S33: =R33*Q33 -> 10530 | T33: =R33+S33 -> 69030 | V33: DEBIT CARD | W33: =COUNTIF($M$2:$M$251,V33) -> 66
A34: TXN033 | B34: 46219 | C34: C033-Divya-Kozhikode | D34: {=_xlfn.TEXTSPLIT(TRIM(C34),"-")} -> C033 | E34: Divya | F34: Kozhikode | G34: P107-Webcam | H34: {=_xlfn.TEXTSPLIT(TRIM(G34),"-")} -> P107 | I34: Webcam | J34: Kozhikode | K34: 8 | L34: 3500 | M34: Debit Card | N34: Anu | O34: =VLOOKUP(H34,Product_Master!$A:$E,3,FALSE) -> Electronics | P34: =VLOOKUP(H34,Product_Master!$A:$E,4,FALSE) -> Logitech | Q34: =VLOOKUP(H34,Product_Master!$A:$E,5,FALSE) -> 0.18 | R34: =K34*L34 -> 28000 | S34: =R34*Q34 -> 5040 | T34: =R34+S34 -> 33040 | V34: UPI | W34: =COUNTIF($M$2:$M$251,V34) -> 61
A35: TXN034 | B35: 46212 | C35: C034-Neha-Thrissur | D35: {=_xlfn.TEXTSPLIT(TRIM(C35),"-")} -> C034 | E35: Neha | F35: Thrissur | G35: P101-Laptop | H35: {=_xlfn.TEXTSPLIT(TRIM(G35),"-")} -> P101 | I35: Laptop | J35: Thrissur | K35: 7 | L35: 55000 | M35: Cash | N35: Suresh | O35: =VLOOKUP(H35,Product_Master!$A:$E,3,FALSE) -> Electronics | P35: =VLOOKUP(H35,Product_Master!$A:$E,4,FALSE) -> Dell | Q35: =VLOOKUP(H35,Product_Master!$A:$E,5,FALSE) -> 0.18 | R35: =K35*L35 -> 385000 | S35: =R35*Q35 -> 69300 | T35: =R35+S35 -> 454300 | V35: CREDIT CARD | W35: =COUNTIF($M$2:$M$251,V35) -> 56
A36: TXN035 | B36: 46213 | C36: C035-Swathi-Alappuzha | D36: {=_xlfn.TEXTSPLIT(TRIM(C36),"-")} -> C035 | E36: Swathi | F36: Alappuzha | G36: P103-Keyboard | H36: {=_xlfn.TEXTSPLIT(TRIM(G36),"-")} -> P103 | I36: Keyboard | J36: Alappuzha | K36: 4 | L36: 1200 | M36: UPI | N36: Asha | O36: =VLOOKUP(H36,Product_Master!$A:$E,3,FALSE) -> Accessories | P36: =VLOOKUP(H36,Product_Master!$A:$E,4,FALSE) -> Logitech | Q36: =VLOOKUP(H36,Product_Master!$A:$E,5,FALSE) -> 0.18 | R36: =K36*L36 -> 4800 | S36: =R36*Q36 -> 864 | T36: =R36+S36 -> 5664
A37: TXN036 | B37: 46205 | C37: C036-Joel-Kochi | D37: {=_xlfn.TEXTSPLIT(TRIM(C37),"-")} -> C036 | E37: Joel | F37: Kochi | G37: P106-Printer | H37: {=_xlfn.TEXTSPLIT(TRIM(G37),"-")} -> P106 | I37: Printer | J37: Kochi | K37: 1 | L37: 12500 | M37: Debit Card | N37: Asha | O37: =VLOOKUP(H37,Product_Master!$A:$E,3,FALSE) -> Electronics | P37: =VLOOKUP(H37,Product_Master!$A:$E,4,FALSE) -> Canon | Q37: =VLOOKUP(H37,Product_Master!$A:$E,5,FALSE) -> 0.18 | R37: =K37*L37 -> 12500 | S37: =R37*Q37 -> 2250 | T37: =R37+S37 -> 14750
A38: TXN037 | B38: 46206 | C38: C037-Meera-Kozhikode | D38: {=_xlfn.TEXTSPLIT(TRIM(C38),"-")} -> C037 | E38: Meera | F38: Kozhikode | G38: P101-Laptop | H38: {=_xlfn.TEXTSPLIT(TRIM(G38),"-")} -> P101 | I38: Laptop | J38: Kozhikode | K38: 9 | L38: 55000 | M38: UPI | N38: Asha | O38: =VLOOKUP(H38,Product_Master!$A:$E,3,FALSE) -> Electronics | P38: =VLOOKUP(H38,Product_Master!$A:$E,4,FALSE) -> Dell | Q38: =VLOOKUP(H38,Product_Master!$A:$E,5,FALSE) -> 0.18 | R38: =K38*L38 -> 495000 | S38: =R38*Q38 -> 89100 | T38: =R38+S38 -> 584100 | V38: SALESPERSON | W38: SALES VALIUE
A39: TXN038 | B39: 46234 | C39: C038-Mohammed-Kannur | D39: {=_xlfn.TEXTSPLIT(TRIM(C39),"-")} -> C038 | E39: Mohammed | F39: Kannur | G39: P107-Webcam | H39: {=_xlfn.TEXTSPLIT(TRIM(G39),"-")} -> P107 | I39: Webcam | J39: Kannur | K39: 2 | L39: 3500 | M39: Credit Card | N39: Asha | O39: =VLOOKUP(H39,Product_Master!$A:$E,3,FALSE) -> Electronics | P39: =VLOOKUP(H39,Product_Master!$A:$E,4,FALSE) -> Logitech | Q39: =VLOOKUP(H39,Product_Master!$A:$E,5,FALSE) -> 0.18 | R39: =K39*L39 -> 7000 | S39: =R39*Q39 -> 1260 | T39: =R39+S39 -> 8260 | V39: SURESH | W39: =SUMIF($N$2:$N$251,V39,$R$2:$R$251) -> 5441050
A40: TXN039 | B40: 46225 | C40: C039-Adithya-Kochi | D40: {=_xlfn.TEXTSPLIT(TRIM(C40),"-")} -> C039 | E40: Adithya | F40: Kochi | G40: P102-Monitor | H40: {=_xlfn.TEXTSPLIT(TRIM(G40),"-")} -> P102 | I40: Monitor | J40: Kochi | K40: 7 | L40: 15000 | M40: Cash | N40: Meera | O40: =VLOOKUP(H40,Product_Master!$A:$E,3,FALSE) -> Electronics | P40: =VLOOKUP(H40,Product_Master!$A:$E,4,FALSE) -> LG | Q40: =VLOOKUP(H40,Product_Master!$A:$E,5,FALSE) -> 0.18 | R40: =K40*L40 -> 105000 | S40: =R40*Q40 -> 18900 | T40: =R40+S40 -> 123900 | V40: MEERA | W40: =SUMIF($N$2:$N$251,V40,$R$2:$R$251) -> 4326500
A41: TXN040 | B41: 46216 | C41: C040-Arjun-Malappuram | D41: {=_xlfn.TEXTSPLIT(TRIM(C41),"-")} -> C040 | E41: Arjun | F41: Malappuram | G41: P104-Mouse | H41: {=_xlfn.TEXTSPLIT(TRIM(G41),"-")} -> P104 | I41: Mouse | J41: Malappuram | K41: 5 | L41: 750 | M41: Cash | N41: Suresh | O41: =VLOOKUP(H41,Product_Master!$A:$E,3,FALSE) -> Accessories | P41: =VLOOKUP(H41,Product_Master!$A:$E,4,FALSE) -> HP | Q41: =VLOOKUP(H41,Product_Master!$A:$E,5,FALSE) -> 0.18 | R41: =K41*L41 -> 3750 | S41: =R41*Q41 -> 675 | T41: =R41+S41 -> 4425 | V41: ANU | W41: =SUMIF($N$2:$N$251,V41,$R$2:$R$251) -> 4209100
A42: TXN041 | B42: 46223 | C42: C041-Nikhil-Trivandrum | D42: {=_xlfn.TEXTSPLIT(TRIM(C42),"-")} -> C041 | E42: Nikhil | F42: Trivandrum | G42: P101-Laptop | H42: {=_xlfn.TEXTSPLIT(TRIM(G42),"-")} -> P101 | I42: Laptop | J42: Trivandrum | K42: 8 | L42: 55000 | M42: UPI | N42: Anu | O42: =VLOOKUP(H42,Product_Master!$A:$E,3,FALSE) -> Electronics | P42: =VLOOKUP(H42,Product_Master!$A:$E,4,FALSE) -> Dell | Q42: =VLOOKUP(H42,Product_Master!$A:$E,5,FALSE) -> 0.18 | R42: =K42*L42 -> 440000 | S42: =R42*Q42 -> 79200 | T42: =R42+S42 -> 519200 | V42: RAVI | W42: =SUMIF($N$2:$N$251,V42,$R$2:$R$251) -> 3734550
A43: TXN042 | B43: 46233 | C43: C042-Ravi-Kannur | D43: {=_xlfn.TEXTSPLIT(TRIM(C43),"-")} -> C042 | E43: Ravi | F43: Kannur | G43: P105-Headphones | H43: {=_xlfn.TEXTSPLIT(TRIM(G43),"-")} -> P105 | I43: Headphones | J43: Kannur | K43: 3 | L43: 2500 | M43: UPI | N43: Ravi | O43: =VLOOKUP(H43,Product_Master!$A:$E,3,FALSE) -> Accessories | P43: =VLOOKUP(H43,Product_Master!$A:$E,4,FALSE) -> Sony | Q43: =VLOOKUP(H43,Product_Master!$A:$E,5,FALSE) -> 0.18 | R43: =K43*L43 -> 7500 | S43: =R43*Q43 -> 1350 | T43: =R43+S43 -> 8850 | V43: ASHA | W43: =SUMIF($N$2:$N$251,V43,$R$2:$R$251) -> 2389350
A44: TXN043 | B44: 46230 | C44: C043-Sneha-Kollam | D44: {=_xlfn.TEXTSPLIT(TRIM(C44),"-")} -> C043 | E44: Sneha | F44: Kollam | G44: P103-Keyboard | H44: {=_xlfn.TEXTSPLIT(TRIM(G44),"-")} -> P103 | I44: Keyboard | J44: Kollam | K44: 8 | L44: 1200 | M44: Cash | N44: Asha | O44: =VLOOKUP(H44,Product_Master!$A:$E,3,FALSE) -> Accessories | P44: =VLOOKUP(H44,Product_Master!$A:$E,4,FALSE) -> Logitech | Q44: =VLOOKUP(H44,Product_Master!$A:$E,5,FALSE) -> 0.18 | R44: =K44*L44 -> 9600 | S44: =R44*Q44 -> 1728 | T44: =R44+S44 -> 11328
A45: TXN044 | B45: 46207 | C45: C044-Nandana-Kochi | D45: {=_xlfn.TEXTSPLIT(TRIM(C45),"-")} -> C044 | E45: Nandana | F45: Kochi | G45: P105-Headphones | H45: {=_xlfn.TEXTSPLIT(TRIM(G45),"-")} -> P105 | I45: Headphones | J45: Kochi | K45: 11 | L45: 2500 | M45: Cash | N45: Anu | O45: =VLOOKUP(H45,Product_Master!$A:$E,3,FALSE) -> Accessories | P45: =VLOOKUP(H45,Product_Master!$A:$E,4,FALSE) -> Sony | Q45: =VLOOKUP(H45,Product_Master!$A:$E,5,FALSE) -> 0.18 | R45: =K45*L45 -> 27500 | S45: =R45*Q45 -> 4950 | T45: =R45+S45 -> 32450 | V45: SALESPERSON GENERATED HIGHEST SALES= | W45: SURESH
A46: TXN045 | B46: 46223 | C46: C045-Priya-Kozhikode | D46: {=_xlfn.TEXTSPLIT(TRIM(C46),"-")} -> C045 | E46: Priya | F46: Kozhikode | G46: P105-Headphones | H46: {=_xlfn.TEXTSPLIT(TRIM(G46),"-")} -> P105 | I46: Headphones | J46: Kozhikode | K46: 5 | L46: 2500 | M46: Cash | N46: Ravi | O46: =VLOOKUP(H46,Product_Master!$A:$E,3,FALSE) -> Accessories | P46: =VLOOKUP(H46,Product_Master!$A:$E,4,FALSE) -> Sony | Q46: =VLOOKUP(H46,Product_Master!$A:$E,5,FALSE) -> 0.18 | R46: =K46*L46 -> 12500 | S46: =R46*Q46 -> 2250 | T46: =R46+S46 -> 14750
A47: TXN046 | B47: 46232 | C47: C046-Farhan-Kollam | D47: {=_xlfn.TEXTSPLIT(TRIM(C47),"-")} -> C046 | E47: Farhan | F47: Kollam | G47: P108-SSD | H47: {=_xlfn.TEXTSPLIT(TRIM(G47),"-")} -> P108 | I47: SSD | J47: Kollam | K47: 5 | L47: 6500 | M47: UPI | N47: Suresh | O47: =VLOOKUP(H47,Product_Master!$A:$E,3,FALSE) -> Storage | P47: =VLOOKUP(H47,Product_Master!$A:$E,4,FALSE) -> Samsung | Q47: =VLOOKUP(H47,Product_Master!$A:$E,5,FALSE) -> 0.18 | R47: =K47*L47 -> 32500 | S47: =R47*Q47 -> 5850 | T47: =R47+S47 -> 38350 | V47: CATEGORY | W47: SALES VALUE
A48: TXN047 | B48: 46228 | C48: C047-Sanjay-Kochi | D48: {=_xlfn.TEXTSPLIT(TRIM(C48),"-")} -> C047 | E48: Sanjay | F48: Kochi | G48: P101-Laptop | H48: {=_xlfn.TEXTSPLIT(TRIM(G48),"-")} -> P101 | I48: Laptop | J48: Kochi | K48: 6 | L48: 55000 | M48: Cash | N48: Ravi | O48: =VLOOKUP(H48,Product_Master!$A:$E,3,FALSE) -> Electronics | P48: =VLOOKUP(H48,Product_Master!$A:$E,4,FALSE) -> Dell | Q48: =VLOOKUP(H48,Product_Master!$A:$E,5,FALSE) -> 0.18 | R48: =K48*L48 -> 330000 | S48: =R48*Q48 -> 59400 | T48: =R48+S48 -> 389400 | V48: ELECTRONICS | W48: =SUMIF($O$2:$O$251,V48,$R$2:$R$251) -> 17902000
A49: TXN048 | B49: 46204 | C49: C048-Joel-Alappuzha | D49: {=_xlfn.TEXTSPLIT(TRIM(C49),"-")} -> C048 | E49: Joel | F49: Alappuzha | G49: P107-Webcam | H49: {=_xlfn.TEXTSPLIT(TRIM(G49),"-")} -> P107 | I49: Webcam | J49: Alappuzha | K49: 9 | L49: 3500 | M49: UPI | N49: Ravi | O49: =VLOOKUP(H49,Product_Master!$A:$E,3,FALSE) -> Electronics | P49: =VLOOKUP(H49,Product_Master!$A:$E,4,FALSE) -> Logitech | Q49: =VLOOKUP(H49,Product_Master!$A:$E,5,FALSE) -> 0.18 | R49: =K49*L49 -> 31500 | S49: =R49*Q49 -> 5670 | T49: =R49+S49 -> 37170 | V49: STORAGE | W49: =SUMIF($O$2:$O$251,V49,$R$2:$R$251) -> 1384500
A50: TXN049 | B50: 46221 | C50: C049-Ravi-Kochi | D50: {=_xlfn.TEXTSPLIT(TRIM(C50),"-")} -> C049 | E50: Ravi | F50: Kochi | G50: P106-Printer | H50: {=_xlfn.TEXTSPLIT(TRIM(G50),"-")} -> P106 | I50: Printer | J50: Kochi | K50: 10 | L50: 12500 | M50: Debit Card | N50: Ravi | O50: =VLOOKUP(H50,Product_Master!$A:$E,3,FALSE) -> Electronics | P50: =VLOOKUP(H50,Product_Master!$A:$E,4,FALSE) -> Canon | Q50: =VLOOKUP(H50,Product_Master!$A:$E,5,FALSE) -> 0.18 | R50: =K50*L50 -> 125000 | S50: =R50*Q50 -> 22500 | T50: =R50+S50 -> 147500 | V50: ACCESSORIES | W50: =SUMIF($O$2:$O$251,V50,$R$2:$R$251) -> 814050
A51: TXN050 | B51: 46232 | C51: C050-Anjali-Kollam | D51: {=_xlfn.TEXTSPLIT(TRIM(C51),"-")} -> C050 | E51: Anjali | F51: Kollam | G51: P106-Printer | H51: {=_xlfn.TEXTSPLIT(TRIM(G51),"-")} -> P106 | I51: Printer | J51: Kollam | K51: 1 | L51: 12500 | M51: Credit Card | N51: Ravi | O51: =VLOOKUP(H51,Product_Master!$A:$E,3,FALSE) -> Electronics | P51: =VLOOKUP(H51,Product_Master!$A:$E,4,FALSE) -> Canon | Q51: =VLOOKUP(H51,Product_Master!$A:$E,5,FALSE) -> 0.18 | R51: =K51*L51 -> 12500 | S51: =R51*Q51 -> 2250 | T51: =R51+S51 -> 14750
A52: TXN051 | B52: 46232 | C52: C051-Farhan-Trivandrum | D52: {=_xlfn.TEXTSPLIT(TRIM(C52),"-")} -> C051 | E52: Farhan | F52: Trivandrum | G52: P106-Printer | H52: {=_xlfn.TEXTSPLIT(TRIM(G52),"-")} -> P106 | I52: Printer | J52: Trivandrum | K52: 9 | L52: 12500 | M52: Credit Card | N52: Ravi | O52: =VLOOKUP(H52,Product_Master!$A:$E,3,FALSE) -> Electronics | P52: =VLOOKUP(H52,Product_Master!$A:$E,4,FALSE) -> Canon | Q52: =VLOOKUP(H52,Product_Master!$A:$E,5,FALSE) -> 0.18 | R52: =K52*L52 -> 112500 | S52: =R52*Q52 -> 20250 | T52: =R52+S52 -> 132750 | V52: CATEGORY GENERATED HIGHEST SALES= | W52: ELECTRONICS
A53: TXN052 | B53: 46209 | C53: C052-Neha-Kozhikode | D53: {=_xlfn.TEXTSPLIT(TRIM(C53),"-")} -> C052 | E53: Neha | F53: Kozhikode | G53: P107-Webcam | H53: {=_xlfn.TEXTSPLIT(TRIM(G53),"-")} -> P107 | I53: Webcam | J53: Kozhikode | K53: 1 | L53: 3500 | M53: Cash | N53: Suresh | O53: =VLOOKUP(H53,Product_Master!$A:$E,3,FALSE) -> Electronics | P53: =VLOOKUP(H53,Product_Master!$A:$E,4,FALSE) -> Logitech | Q53: =VLOOKUP(H53,Product_Master!$A:$E,5,FALSE) -> 0.18 | R53: =K53*L53 -> 3500 | S53: =R53*Q53 -> 630 | T53: =R53+S53 -> 4130
A54: TXN053 | B54: 46229 | C54: C053-Farhan-Kannur | D54: {=_xlfn.TEXTSPLIT(TRIM(C54),"-")} -> C053 | E54: Farhan | F54: Kannur | G54: P105-Headphones | H54: {=_xlfn.TEXTSPLIT(TRIM(G54),"-")} -> P105 | I54: Headphones | J54: Kannur | K54: 3 | L54: 2500 | M54: UPI | N54: Suresh | O54: =VLOOKUP(H54,Product_Master!$A:$E,3,FALSE) -> Accessories | P54: =VLOOKUP(H54,Product_Master!$A:$E,4,FALSE) -> Sony | Q54: =VLOOKUP(H54,Product_Master!$A:$E,5,FALSE) -> 0.18 | R54: =K54*L54 -> 7500 | S54: =R54*Q54 -> 1350 | T54: =R54+S54 -> 8850
A55: TXN054 | B55: 46230 | C55: C054-Anjali-Alappuzha | D55: {=_xlfn.TEXTSPLIT(TRIM(C55),"-")} -> C054 | E55: Anjali | F55: Alappuzha | G55: P104-Mouse | H55: {=_xlfn.TEXTSPLIT(TRIM(G55),"-")} -> P104 | I55: Mouse | J55: Alappuzha | K55: 4 | L55: 750 | M55: Cash | N55: Meera | O55: =VLOOKUP(H55,Product_Master!$A:$E,3,FALSE) -> Accessories | P55: =VLOOKUP(H55,Product_Master!$A:$E,4,FALSE) -> HP | Q55: =VLOOKUP(H55,Product_Master!$A:$E,5,FALSE) -> 0.18 | R55: =K55*L55 -> 3000 | S55: =R55*Q55 -> 540 | T55: =R55+S55 -> 3540 | V55: STATEMENT | W55: FUNCTION USED | X55: RESULT
A56: TXN055 | B56: 46210 | C56: C055-Divya-Kannur | D56: {=_xlfn.TEXTSPLIT(TRIM(C56),"-")} -> C055 | E56: Divya | F56: Kannur | G56: P101-Laptop | H56: {=_xlfn.TEXTSPLIT(TRIM(G56),"-")} -> P101 | I56: Laptop | J56: Kannur | K56: 11 | L56: 55000 | M56: Cash | N56: Meera | O56: =VLOOKUP(H56,Product_Master!$A:$E,3,FALSE) -> Electronics | P56: =VLOOKUP(H56,Product_Master!$A:$E,4,FALSE) -> Dell | Q56: =VLOOKUP(H56,Product_Master!$A:$E,5,FALSE) -> 0.18 | R56: =K56*L56 -> 605000 | S56: =R56*Q56 -> 108900 | T56: =R56+S56 -> 713900 | V56: GIVE THE ID OF 1ST CUSTOMER | W56: LEFT() | X56: =LEFT(C2,4) -> C001
A57: TXN056 | B57: 46220 | C57: C056-Mohammed-Kollam | D57: {=_xlfn.TEXTSPLIT(TRIM(C57),"-")} -> C056 | E57: Mohammed | F57: Kollam | G57: P106-Printer | H57: {=_xlfn.TEXTSPLIT(TRIM(G57),"-")} -> P106 | I57: Printer | J57: Kollam | K57: 11 | L57: 12500 | M57: Cash | N57: Anu | O57: =VLOOKUP(H57,Product_Master!$A:$E,3,FALSE) -> Electronics | P57: =VLOOKUP(H57,Product_Master!$A:$E,4,FALSE) -> Canon | Q57: =VLOOKUP(H57,Product_Master!$A:$E,5,FALSE) -> 0.18 | R57: =K57*L57 -> 137500 | S57: =R57*Q57 -> 24750 | T57: =R57+S57 -> 162250 | V57: GIVE THE NAME OF 1ST CUSTOMER | W57: MID() | X57: =MID(C2,6,7) -> Nandana
A58: TXN057 | B58: 46234 | C58: C057-Priya-Kollam | D58: {=_xlfn.TEXTSPLIT(TRIM(C58),"-")} -> C057 | E58: Priya | F58: Kollam | G58: P103-Keyboard | H58: {=_xlfn.TEXTSPLIT(TRIM(G58),"-")} -> P103 | I58: Keyboard | J58: Kollam | K58: 10 | L58: 1200 | M58: UPI | N58: Anu | O58: =VLOOKUP(H58,Product_Master!$A:$E,3,FALSE) -> Accessories | P58: =VLOOKUP(H58,Product_Master!$A:$E,4,FALSE) -> Logitech | Q58: =VLOOKUP(H58,Product_Master!$A:$E,5,FALSE) -> 0.18 | R58: =K58*L58 -> 12000 | S58: =R58*Q58 -> 2160 | T58: =R58+S58 -> 14160 | V58: 1ST CUSTOMER NAME TO LOWER CASE | W58: LOWER() | X58: =LOWER(E2) -> nandana
A59: TXN058 | B59: 46229 | C59: C058-Adithya-Thrissur | D59: {=_xlfn.TEXTSPLIT(TRIM(C59),"-")} -> C058 | E59: Adithya | F59: Thrissur | G59: P106-Printer | H59: {=_xlfn.TEXTSPLIT(TRIM(G59),"-")} -> P106 | I59: Printer | J59: Thrissur | K59: 12 | L59: 12500 | M59: Debit Card | N59: Asha | O59: =VLOOKUP(H59,Product_Master!$A:$E,3,FALSE) -> Electronics | P59: =VLOOKUP(H59,Product_Master!$A:$E,4,FALSE) -> Canon | Q59: =VLOOKUP(H59,Product_Master!$A:$E,5,FALSE) -> 0.18 | R59: =K59*L59 -> 150000 | S59: =R59*Q59 -> 27000 | T59: =R59+S59 -> 177000 | V59: 1ST CUSTOMER NAME TO UPPER CASE | W59: UPPER() | X59: =UPPER(E2) -> NANDANA
A60: TXN059 | B60: 46210 | C60: C059-Meera-Trivandrum | D60: {=_xlfn.TEXTSPLIT(TRIM(C60),"-")} -> C059 | E60: Meera | F60: Trivandrum | G60: P107-Webcam | H60: {=_xlfn.TEXTSPLIT(TRIM(G60),"-")} -> P107 | I60: Webcam | J60: Trivandrum | K60: 10 | L60: 3500 | M60: UPI | N60: Suresh | O60: =VLOOKUP(H60,Product_Master!$A:$E,3,FALSE) -> Electronics | P60: =VLOOKUP(H60,Product_Master!$A:$E,4,FALSE) -> Logitech | Q60: =VLOOKUP(H60,Product_Master!$A:$E,5,FALSE) -> 0.18 | R60: =K60*L60 -> 35000 | S60: =R60*Q60 -> 6300 | T60: =R60+S60 -> 41300 | V60: DISPLAY CATOGORY WITH PRODUCT NAME | W60: CONCAT() | X60: =_xlfn.CONCAT(I2,"-",O2) -> Laptop-Electronics
A61: TXN060 | B61: 46206 | C61: C060-Rahul-Kannur | D61: {=_xlfn.TEXTSPLIT(TRIM(C61),"-")} -> C060 | E61: Rahul | F61: Kannur | G61: P106-Printer | H61: {=_xlfn.TEXTSPLIT(TRIM(G61),"-")} -> P106 | I61: Printer | J61: Kannur | K61: 7 | L61: 12500 | M61: Cash | N61: Asha | O61: =VLOOKUP(H61,Product_Master!$A:$E,3,FALSE) -> Electronics | P61: =VLOOKUP(H61,Product_Master!$A:$E,4,FALSE) -> Canon | Q61: =VLOOKUP(H61,Product_Master!$A:$E,5,FALSE) -> 0.18 | R61: =K61*L61 -> 87500 | S61: =R61*Q61 -> 15750 | T61: =R61+S61 -> 103250 | V61: SPLIT COSTUMER INFO | W61: TEXTSPLIT() | X61: {=_xlfn.TEXTSPLIT(C2,"-")} -> C001 | Y61: Nandana | Z61: Trivandrum
A62: TXN061 | B62: 46213 | C62: C061-Nikhil-Trivandrum | D62: {=_xlfn.TEXTSPLIT(TRIM(C62),"-")} -> C061 | E62: Nikhil | F62: Trivandrum | G62: P105-Headphones | H62: {=_xlfn.TEXTSPLIT(TRIM(G62),"-")} -> P105 | I62: Headphones | J62: Trivandrum | K62: 9 | L62: 2500 | M62: Debit Card | N62: Meera | O62: =VLOOKUP(H62,Product_Master!$A:$E,3,FALSE) -> Accessories | P62: =VLOOKUP(H62,Product_Master!$A:$E,4,FALSE) -> Sony | Q62: =VLOOKUP(H62,Product_Master!$A:$E,5,FALSE) -> 0.18 | R62: =K62*L62 -> 22500 | S62: =R62*Q62 -> 4050 | T62: =R62+S62 -> 26550 | V62: LENGTH OF NAME OF 1ST CUSTOMER | W62: LEN() | X62: =LEN(E2) -> 7
A63: TXN062 | B63: 46217 | C63: C062-Vishnu-Kollam | D63: {=_xlfn.TEXTSPLIT(TRIM(C63),"-")} -> C062 | E63: Vishnu | F63: Kollam | G63: P103-Keyboard | H63: {=_xlfn.TEXTSPLIT(TRIM(G63),"-")} -> P103 | I63: Keyboard | J63: Kollam | K63: 4 | L63: 1200 | M63: Debit Card | N63: Ravi | O63: =VLOOKUP(H63,Product_Master!$A:$E,3,FALSE) -> Accessories | P63: =VLOOKUP(H63,Product_Master!$A:$E,4,FALSE) -> Logitech | Q63: =VLOOKUP(H63,Product_Master!$A:$E,5,FALSE) -> 0.18 | R63: =K63*L63 -> 4800 | S63: =R63*Q63 -> 864 | T63: =R63+S63 -> 5664
A64: TXN063 | B64: 46230 | C64: C063-Adithya-Kollam | D64: {=_xlfn.TEXTSPLIT(TRIM(C64),"-")} -> C063 | E64: Adithya | F64: Kollam | G64: P107-Webcam | H64: {=_xlfn.TEXTSPLIT(TRIM(G64),"-")} -> P107 | I64: Webcam | J64: Kollam | K64: 9 | L64: 3500 | M64: Cash | N64: Meera | O64: =VLOOKUP(H64,Product_Master!$A:$E,3,FALSE) -> Electronics | P64: =VLOOKUP(H64,Product_Master!$A:$E,4,FALSE) -> Logitech | Q64: =VLOOKUP(H64,Product_Master!$A:$E,5,FALSE) -> 0.18 | R64: =K64*L64 -> 31500 | S64: =R64*Q64 -> 5670 | T64: =R64+S64 -> 37170
A65: TXN064 | B65: 46218 | C65: C064-Arjun-Thrissur | D65: {=_xlfn.TEXTSPLIT(TRIM(C65),"-")} -> C064 | E65: Arjun | F65: Thrissur | G65: P106-Printer | H65: {=_xlfn.TEXTSPLIT(TRIM(G65),"-")} -> P106 | I65: Printer | J65: Thrissur | K65: 8 | L65: 12500 | M65: Credit Card | N65: Asha | O65: =VLOOKUP(H65,Product_Master!$A:$E,3,FALSE) -> Electronics | P65: =VLOOKUP(H65,Product_Master!$A:$E,4,FALSE) -> Canon | Q65: =VLOOKUP(H65,Product_Master!$A:$E,5,FALSE) -> 0.18 | R65: =K65*L65 -> 100000 | S65: =R65*Q65 -> 18000 | T65: =R65+S65 -> 118000 | V65: PRODUCT | W65: SALES VALUE
A66: TXN065 | B66: 46220 | C66: C065-Kiran-Kozhikode | D66: {=_xlfn.TEXTSPLIT(TRIM(C66),"-")} -> C065 | E66: Kiran | F66: Kozhikode | G66: P102-Monitor | H66: {=_xlfn.TEXTSPLIT(TRIM(G66),"-")} -> P102 | I66: Monitor | J66: Kozhikode | K66: 5 | L66: 15000 | M66: Cash | N66: Anu | O66: =VLOOKUP(H66,Product_Master!$A:$E,3,FALSE) -> Electronics | P66: =VLOOKUP(H66,Product_Master!$A:$E,4,FALSE) -> LG | Q66: =VLOOKUP(H66,Product_Master!$A:$E,5,FALSE) -> 0.18 | R66: =K66*L66 -> 75000 | S66: =R66*Q66 -> 13500 | T66: =R66+S66 -> 88500 | V66: Laptop | W66: =SUMIF($I$2:$I$251,V66,$R$2:$R$251) -> 10285000
A67: TXN066 | B67: 46208 | C67: C066-Divya-Kollam | D67: {=_xlfn.TEXTSPLIT(TRIM(C67),"-")} -> C066 | E67: Divya | F67: Kollam | G67: P104-Mouse | H67: {=_xlfn.TEXTSPLIT(TRIM(G67),"-")} -> P104 | I67: Mouse | J67: Kollam | K67: 4 | L67: 750 | M67: UPI | N67: Ravi | O67: =VLOOKUP(H67,Product_Master!$A:$E,3,FALSE) -> Accessories | P67: =VLOOKUP(H67,Product_Master!$A:$E,4,FALSE) -> HP | Q67: =VLOOKUP(H67,Product_Master!$A:$E,5,FALSE) -> 0.18 | R67: =K67*L67 -> 3000 | S67: =R67*Q67 -> 540 | T67: =R67+S67 -> 3540 | V67: Monitor | W67: =SUMIF($I$2:$I$251,V67,$R$2:$R$251) -> 3690000
A68: TXN067 | B68: 46232 | C68: C067-Kiran-Trivandrum | D68: {=_xlfn.TEXTSPLIT(TRIM(C68),"-")} -> C067 | E68: Kiran | F68: Trivandrum | G68: P108-SSD | H68: {=_xlfn.TEXTSPLIT(TRIM(G68),"-")} -> P108 | I68: SSD | J68: Trivandrum | K68: 7 | L68: 6500 | M68: Credit Card | N68: Suresh | O68: =VLOOKUP(H68,Product_Master!$A:$E,3,FALSE) -> Storage | P68: =VLOOKUP(H68,Product_Master!$A:$E,4,FALSE) -> Samsung | Q68: =VLOOKUP(H68,Product_Master!$A:$E,5,FALSE) -> 0.18 | R68: =K68*L68 -> 45500 | S68: =R68*Q68 -> 8190 | T68: =R68+S68 -> 53690 | V68: Printer | W68: =SUMIF($I$2:$I$251,V68,$R$2:$R$251) -> 3062500
A69: TXN068 | B69: 46224 | C69: C068-Kiran-Thrissur | D69: {=_xlfn.TEXTSPLIT(TRIM(C69),"-")} -> C068 | E69: Kiran | F69: Thrissur | G69: P104-Mouse | H69: {=_xlfn.TEXTSPLIT(TRIM(G69),"-")} -> P104 | I69: Mouse | J69: Thrissur | K69: 3 | L69: 750 | M69: UPI | N69: Anu | O69: =VLOOKUP(H69,Product_Master!$A:$E,3,FALSE) -> Accessories | P69: =VLOOKUP(H69,Product_Master!$A:$E,4,FALSE) -> HP | Q69: =VLOOKUP(H69,Product_Master!$A:$E,5,FALSE) -> 0.18 | R69: =K69*L69 -> 2250 | S69: =R69*Q69 -> 405 | T69: =R69+S69 -> 2655 | V69: SSD | W69: =SUMIF($I$2:$I$251,V69,$R$2:$R$251) -> 1384500
A70: TXN069 | B70: 46220 | C70: C069-Amal-Kannur | D70: {=_xlfn.TEXTSPLIT(TRIM(C70),"-")} -> C069 | E70: Amal | F70: Kannur | G70: P103-Keyboard | H70: {=_xlfn.TEXTSPLIT(TRIM(G70),"-")} -> P103 | I70: Keyboard | J70: Kannur | K70: 12 | L70: 1200 | M70: UPI | N70: Asha | O70: =VLOOKUP(H70,Product_Master!$A:$E,3,FALSE) -> Accessories | P70: =VLOOKUP(H70,Product_Master!$A:$E,4,FALSE) -> Logitech | Q70: =VLOOKUP(H70,Product_Master!$A:$E,5,FALSE) -> 0.18 | R70: =K70*L70 -> 14400 | S70: =R70*Q70 -> 2592 | T70: =R70+S70 -> 16992 | V70: Webcam | W70: =SUMIF($I$2:$I$251,V70,$R$2:$R$251) -> 864500
A71: TXN070 | B71: 46229 | C71: C070-Divya-Trivandrum | D71: {=_xlfn.TEXTSPLIT(TRIM(C71),"-")} -> C070 | E71: Divya | F71: Trivandrum | G71: P108-SSD | H71: {=_xlfn.TEXTSPLIT(TRIM(G71),"-")} -> P108 | I71: SSD | J71: Trivandrum | K71: 3 | L71: 6500 | M71: Cash | N71: Suresh | O71: =VLOOKUP(H71,Product_Master!$A:$E,3,FALSE) -> Storage | P71: =VLOOKUP(H71,Product_Master!$A:$E,4,FALSE) -> Samsung | Q71: =VLOOKUP(H71,Product_Master!$A:$E,5,FALSE) -> 0.18 | R71: =K71*L71 -> 19500 | S71: =R71*Q71 -> 3510 | T71: =R71+S71 -> 23010 | V71: Headphones | W71: =SUMIF($I$2:$I$251,V71,$R$2:$R$251) -> 502500
A72: TXN071 | B72: 46227 | C72: C071-Adithya-Thrissur | D72: {=_xlfn.TEXTSPLIT(TRIM(C72),"-")} -> C071 | E72: Adithya | F72: Thrissur | G72: P108-SSD | H72: {=_xlfn.TEXTSPLIT(TRIM(G72),"-")} -> P108 | I72: SSD | J72: Thrissur | K72: 3 | L72: 6500 | M72: Debit Card | N72: Meera | O72: =VLOOKUP(H72,Product_Master!$A:$E,3,FALSE) -> Storage | P72: =VLOOKUP(H72,Product_Master!$A:$E,4,FALSE) -> Samsung | Q72: =VLOOKUP(H72,Product_Master!$A:$E,5,FALSE) -> 0.18 | R72: =K72*L72 -> 19500 | S72: =R72*Q72 -> 3510 | T72: =R72+S72 -> 23010 | V72: Keyboard | W72: =SUMIF($I$2:$I$251,V72,$R$2:$R$251) -> 244800
A73: TXN072 | B73: 46211 | C73: C072-Divya-Kollam | D73: {=_xlfn.TEXTSPLIT(TRIM(C73),"-")} -> C072 | E73: Divya | F73: Kollam | G73: P108-SSD | H73: {=_xlfn.TEXTSPLIT(TRIM(G73),"-")} -> P108 | I73: SSD | J73: Kollam | K73: 11 | L73: 6500 | M73: Debit Card | N73: Anu | O73: =VLOOKUP(H73,Product_Master!$A:$E,3,FALSE) -> Storage | P73: =VLOOKUP(H73,Product_Master!$A:$E,4,FALSE) -> Samsung | Q73: =VLOOKUP(H73,Product_Master!$A:$E,5,FALSE) -> 0.18 | R73: =K73*L73 -> 71500 | S73: =R73*Q73 -> 12870 | T73: =R73+S73 -> 84370 | V73: Mouse | W73: =SUMIF($I$2:$I$251,V73,$R$2:$R$251) -> 66750
A74: TXN073 | B74: 46214 | C74: C073-Swathi-Kollam | D74: {=_xlfn.TEXTSPLIT(TRIM(C74),"-")} -> C073 | E74: Swathi | F74: Kollam | G74: P104-Mouse | H74: {=_xlfn.TEXTSPLIT(TRIM(G74),"-")} -> P104 | I74: Mouse | J74: Kollam | K74: 5 | L74: 750 | M74: UPI | N74: Ravi | O74: =VLOOKUP(H74,Product_Master!$A:$E,3,FALSE) -> Accessories | P74: =VLOOKUP(H74,Product_Master!$A:$E,4,FALSE) -> HP | Q74: =VLOOKUP(H74,Product_Master!$A:$E,5,FALSE) -> 0.18 | R74: =K74*L74 -> 3750 | S74: =R74*Q74 -> 675 | T74: =R74+S74 -> 4425
A75: TXN074 | B75: 46208 | C75: C074-Akhil-Kannur | D75: {=_xlfn.TEXTSPLIT(TRIM(C75),"-")} -> C074 | E75: Akhil | F75: Kannur | G75: P107-Webcam | H75: {=_xlfn.TEXTSPLIT(TRIM(G75),"-")} -> P107 | I75: Webcam | J75: Kannur | K75: 12 | L75: 3500 | M75: Credit Card | N75: Anu | O75: =VLOOKUP(H75,Product_Master!$A:$E,3,FALSE) -> Electronics | P75: =VLOOKUP(H75,Product_Master!$A:$E,4,FALSE) -> Logitech | Q75: =VLOOKUP(H75,Product_Master!$A:$E,5,FALSE) -> 0.18 | R75: =K75*L75 -> 42000 | S75: =R75*Q75 -> 7560 | T75: =R75+S75 -> 49560 | V75: TOP PRODUCT= | W75: LAPTOP
A76: TXN075 | B76: 46218 | C76: C075-Amal-Thrissur | D76: {=_xlfn.TEXTSPLIT(TRIM(C76),"-")} -> C075 | E76: Amal | F76: Thrissur | G76: P106-Printer | H76: {=_xlfn.TEXTSPLIT(TRIM(G76),"-")} -> P106 | I76: Printer | J76: Thrissur | K76: 9 | L76: 12500 | M76: UPI | N76: Ravi | O76: =VLOOKUP(H76,Product_Master!$A:$E,3,FALSE) -> Electronics | P76: =VLOOKUP(H76,Product_Master!$A:$E,4,FALSE) -> Canon | Q76: =VLOOKUP(H76,Product_Master!$A:$E,5,FALSE) -> 0.18 | R76: =K76*L76 -> 112500 | S76: =R76*Q76 -> 20250 | T76: =R76+S76 -> 132750
A77: TXN076 | B77: 46216 | C77: C076-Amal-Thrissur | D77: {=_xlfn.TEXTSPLIT(TRIM(C77),"-")} -> C076 | E77: Amal | F77: Thrissur | G77: P101-Laptop | H77: {=_xlfn.TEXTSPLIT(TRIM(G77),"-")} -> P101 | I77: Laptop | J77: Thrissur | K77: 10 | L77: 55000 | M77: UPI | N77: Meera | O77: =VLOOKUP(H77,Product_Master!$A:$E,3,FALSE) -> Electronics | P77: =VLOOKUP(H77,Product_Master!$A:$E,4,FALSE) -> Dell | Q77: =VLOOKUP(H77,Product_Master!$A:$E,5,FALSE) -> 0.18 | R77: =K77*L77 -> 550000 | S77: =R77*Q77 -> 99000 | T77: =R77+S77 -> 649000
A78: TXN077 | B78: 46227 | C78: C077-Fathima-Thrissur | D78: {=_xlfn.TEXTSPLIT(TRIM(C78),"-")} -> C077 | E78: Fathima | F78: Thrissur | G78: P107-Webcam | H78: {=_xlfn.TEXTSPLIT(TRIM(G78),"-")} -> P107 | I78: Webcam | J78: Thrissur | K78: 9 | L78: 3500 | M78: Credit Card | N78: Suresh | O78: =VLOOKUP(H78,Product_Master!$A:$E,3,FALSE) -> Electronics | P78: =VLOOKUP(H78,Product_Master!$A:$E,4,FALSE) -> Logitech | Q78: =VLOOKUP(H78,Product_Master!$A:$E,5,FALSE) -> 0.18 | R78: =K78*L78 -> 31500 | S78: =R78*Q78 -> 5670 | T78: =R78+S78 -> 37170
A79: TXN078 | B79: 46204 | C79: C078-Divya-Kollam | D79: {=_xlfn.TEXTSPLIT(TRIM(C79),"-")} -> C078 | E79: Divya | F79: Kollam | G79: P107-Webcam | H79: {=_xlfn.TEXTSPLIT(TRIM(G79),"-")} -> P107 | I79: Webcam | J79: Kollam | K79: 8 | L79: 3500 | M79: Cash | N79: Suresh | O79: =VLOOKUP(H79,Product_Master!$A:$E,3,FALSE) -> Electronics | P79: =VLOOKUP(H79,Product_Master!$A:$E,4,FALSE) -> Logitech | Q79: =VLOOKUP(H79,Product_Master!$A:$E,5,FALSE) -> 0.18 | R79: =K79*L79 -> 28000 | S79: =R79*Q79 -> 5040 | T79: =R79+S79 -> 33040
A80: TXN079 | B80: 46223 | C80: C079-Joel-Kozhikode | D80: {=_xlfn.TEXTSPLIT(TRIM(C80),"-")} -> C079 | E80: Joel | F80: Kozhikode | G80: P108-SSD | H80: {=_xlfn.TEXTSPLIT(TRIM(G80),"-")} -> P108 | I80: SSD | J80: Kozhikode | K80: 3 | L80: 6500 | M80: UPI | N80: Suresh | O80: =VLOOKUP(H80,Product_Master!$A:$E,3,FALSE) -> Storage | P80: =VLOOKUP(H80,Product_Master!$A:$E,4,FALSE) -> Samsung | Q80: =VLOOKUP(H80,Product_Master!$A:$E,5,FALSE) -> 0.18 | R80: =K80*L80 -> 19500 | S80: =R80*Q80 -> 3510 | T80: =R80+S80 -> 23010
A81: TXN080 | B81: 46217 | C81: C080-Asha-Kochi | D81: {=_xlfn.TEXTSPLIT(TRIM(C81),"-")} -> C080 | E81: Asha | F81: Kochi | G81: P102-Monitor | H81: {=_xlfn.TEXTSPLIT(TRIM(G81),"-")} -> P102 | I81: Monitor | J81: Kochi | K81: 11 | L81: 15000 | M81: Debit Card | N81: Ravi | O81: =VLOOKUP(H81,Product_Master!$A:$E,3,FALSE) -> Electronics | P81: =VLOOKUP(H81,Product_Master!$A:$E,4,FALSE) -> LG | Q81: =VLOOKUP(H81,Product_Master!$A:$E,5,FALSE) -> 0.18 | R81: =K81*L81 -> 165000 | S81: =R81*Q81 -> 29700 | T81: =R81+S81 -> 194700
A82: TXN081 | B82: 46210 | C82: C081-Anjali-Kollam | D82: {=_xlfn.TEXTSPLIT(TRIM(C82),"-")} -> C081 | E82: Anjali | F82: Kollam | G82: P107-Webcam | H82: {=_xlfn.TEXTSPLIT(TRIM(G82),"-")} -> P107 | I82: Webcam | J82: Kollam | K82: 6 | L82: 3500 | M82: Cash | N82: Meera | O82: =VLOOKUP(H82,Product_Master!$A:$E,3,FALSE) -> Electronics | P82: =VLOOKUP(H82,Product_Master!$A:$E,4,FALSE) -> Logitech | Q82: =VLOOKUP(H82,Product_Master!$A:$E,5,FALSE) -> 0.18 | R82: =K82*L82 -> 21000 | S82: =R82*Q82 -> 3780 | T82: =R82+S82 -> 24780
A83: TXN082 | B83: 46230 | C83: C082-Vishnu-Kollam | D83: {=_xlfn.TEXTSPLIT(TRIM(C83),"-")} -> C082 | E83: Vishnu | F83: Kollam | G83: P107-Webcam | H83: {=_xlfn.TEXTSPLIT(TRIM(G83),"-")} -> P107 | I83: Webcam | J83: Kollam | K83: 5 | L83: 3500 | M83: Debit Card | N83: Anu | O83: =VLOOKUP(H83,Product_Master!$A:$E,3,FALSE) -> Electronics | P83: =VLOOKUP(H83,Product_Master!$A:$E,4,FALSE) -> Logitech | Q83: =VLOOKUP(H83,Product_Master!$A:$E,5,FALSE) -> 0.18 | R83: =K83*L83 -> 17500 | S83: =R83*Q83 -> 3150 | T83: =R83+S83 -> 20650
A84: TXN083 | B84: 46224 | C84: C083-Joel-Kochi | D84: {=_xlfn.TEXTSPLIT(TRIM(C84),"-")} -> C083 | E84: Joel | F84: Kochi | G84: P106-Printer | H84: {=_xlfn.TEXTSPLIT(TRIM(G84),"-")} -> P106 | I84: Printer | J84: Kochi | K84: 4 | L84: 12500 | M84: UPI | N84: Anu | O84: =VLOOKUP(H84,Product_Master!$A:$E,3,FALSE) -> Electronics | P84: =VLOOKUP(H84,Product_Master!$A:$E,4,FALSE) -> Canon | Q84: =VLOOKUP(H84,Product_Master!$A:$E,5,FALSE) -> 0.18 | R84: =K84*L84 -> 50000 | S84: =R84*Q84 -> 9000 | T84: =R84+S84 -> 59000
A85: TXN084 | B85: 46208 | C85: C084-Divya-Kannur | D85: {=_xlfn.TEXTSPLIT(TRIM(C85),"-")} -> C084 | E85: Divya | F85: Kannur | G85: P101-Laptop | H85: {=_xlfn.TEXTSPLIT(TRIM(G85),"-")} -> P101 | I85: Laptop | J85: Kannur | K85: 10 | L85: 55000 | M85: Credit Card | N85: Suresh | O85: =VLOOKUP(H85,Product_Master!$A:$E,3,FALSE) -> Electronics | P85: =VLOOKUP(H85,Product_Master!$A:$E,4,FALSE) -> Dell | Q85: =VLOOKUP(H85,Product_Master!$A:$E,5,FALSE) -> 0.18 | R85: =K85*L85 -> 550000 | S85: =R85*Q85 -> 99000 | T85: =R85+S85 -> 649000
A86: TXN085 | B86: 46226 | C86: C085-Farhan-Trivandrum | D86: {=_xlfn.TEXTSPLIT(TRIM(C86),"-")} -> C085 | E86: Farhan | F86: Trivandrum | G86: P104-Mouse | H86: {=_xlfn.TEXTSPLIT(TRIM(G86),"-")} -> P104 | I86: Mouse | J86: Trivandrum | K86: 8 | L86: 750 | M86: Cash | N86: Ravi | O86: =VLOOKUP(H86,Product_Master!$A:$E,3,FALSE) -> Accessories | P86: =VLOOKUP(H86,Product_Master!$A:$E,4,FALSE) -> HP | Q86: =VLOOKUP(H86,Product_Master!$A:$E,5,FALSE) -> 0.18 | R86: =K86*L86 -> 6000 | S86: =R86*Q86 -> 1080 | T86: =R86+S86 -> 7080
A87: TXN086 | B87: 46207 | C87: C086-Adithya-Trivandrum | D87: {=_xlfn.TEXTSPLIT(TRIM(C87),"-")} -> C086 | E87: Adithya | F87: Trivandrum | G87: P103-Keyboard | H87: {=_xlfn.TEXTSPLIT(TRIM(G87),"-")} -> P103 | I87: Keyboard | J87: Trivandrum | K87: 5 | L87: 1200 | M87: UPI | N87: Meera | O87: =VLOOKUP(H87,Product_Master!$A:$E,3,FALSE) -> Accessories | P87: =VLOOKUP(H87,Product_Master!$A:$E,4,FALSE) -> Logitech | Q87: =VLOOKUP(H87,Product_Master!$A:$E,5,FALSE) -> 0.18 | R87: =K87*L87 -> 6000 | S87: =R87*Q87 -> 1080 | T87: =R87+S87 -> 7080
... A251: TXN250 | B251: 46208 | C251: C250-Amal-Kochi | D251: {=_xlfn.TEXTSPLIT(TRIM(C251),"-")} -> C250 | E251: Amal | F251: Kochi | G251: P102-Monitor | H251: {=_xlfn.TEXTSPLIT(TRIM(G251),"-")} -> P102 | I251: Monitor | J251: Kochi | K251: 9 | L251: 15000 | M251: Credit Card | N251: Ravi | O251: =VLOOKUP(H251,Product_Master!$A:$E,3,FALSE) -> Electronics | P251: =VLOOKUP(H251,Product_Master!$A:$E,4,FALSE) -> LG | Q251: =VLOOKUP(H251,Product_Master!$A:$E,5,FALSE) -> 0.18 | R251: =K251*L251 -> 135000 | S251: =R251*Q251 -> 24300 | T251: =R251+S251 -> 159300

Sheet SUMMARY
A1: SUMMARY | B1: RESULT
A3: TOTAL TRANSACTIONS= | B3: 250
A5: TOTAL QUANTITY SOLD= | B5: 1632
A7: TOTAL SALES VALUE= | B7: 20100550
A9: AVERAGE TRANSATION VALUE= | B9: 94874.596
A11: MINIMUM TRANSACTION VALUE= | B11: 885
A13: HIGHEST TRANSATION VALUE= | B13: 778800
A15: TOP SALESPERSON= | B15: SURESH
A17: TOP LOCATION= | B17: THRISSUR
A19: TOP PRODUCT= | B19: LAPTOP
A21: TOP CATEGORY= | B21: ELECTRONICS
A23: MOST USED PAYMENT= | B23: CASH

Sheet Product_Master
A1: Product_ID | B1: Product_Name | C1: Category | D1: Brand | E1: GST_Rate
A2: P101 | B2: Laptop | C2: Electronics | D2: Dell | E2: 0.18
A3: P102 | B3: Monitor | C3: Electronics | D3: LG | E3: 0.18
A4: P103 | B4: Keyboard | C4: Accessories | D4: Logitech | E4: 0.18
A5: P104 | B5: Mouse | C5: Accessories | D5: HP | E5: 0.18
A6: P105 | B6: Headphones | C6: Accessories | D6: Sony | E6: 0.18
A7: P106 | B7: Printer | C7: Electronics | D7: Canon | E7: 0.18
A8: P107 | B8: Webcam | C8: Electronics | D8: Logitech | E8: 0.18
A9: P108 | B9: SSD | C9: Storage | D9: Samsung | E9: 0.18
